docs/conf.py
simim/__init__.py
simim/_handlers.py
simim/_paths.py
simim/_pltsetup.py
simim/constants.py
simim/galprops/__init__.py
simim/galprops/galprops.py
simim/galprops/galprops_am.py
simim/galprops/galprops_builtin.py
simim/galprops/line_co.py
simim/galprops/line_co_dutycycle.py
simim/galprops/line_densegas.py
simim/galprops/line_fir.py
simim/galprops/line_fir_yang.py
simim/galprops/log10normal.py
simim/galprops/sfr_behroozi13.py
simim/galprops/sfr_bethermin17.py
simim/galprops/sfr_ir.py
simim/instrument/__init__.py
simim/instrument/_helpers.py
simim/instrument/instrument.py
simim/instrument/noise_functions.py
simim/instrument/spatial_response.py
simim/instrument/spectral_response.py
simim/lightcone/__init__.py
simim/lightcone/lchandler.py
simim/lightcone/lcmaker.py
simim/map/__init__.py
simim/map/gridder.py
simim/resources/behroozi13_release.dat
simim/siminterface/__init__.py
simim/siminterface/_illustris_datahandling.py
simim/siminterface/_rawsiminterface.py
simim/siminterface/_sims.py
simim/siminterface/illustris.py
simim/siminterface/simhandler.py
simim/siminterface/uchuu.py
simim/siminterface/universemachine.py
simim_dev/dev_features.py
simim_dev/dev_lim_stats.py
simim_dev/dev_spectral_functions.py
simim_dev/old_obs_noise.py
simim_dev/old_obs_radio.py
tests/make_testbox_resource.py
tests/test_gridder.py
tests/test_imports.py
tests/test_instrument.py
tests/test_rawsiminterface.py
tests/test_rawsiminterface2.py
tests/test_siminterface.py
tests/test_spec_gridder.py
tests/by_eye_checks/e2e_sfr.py
tests/old_test_code/lightcone.py
simim-0.3.10.dist-info/LICENSE
simim-0.3.10.dist-info/METADATA
simim-0.3.10.dist-info/WHEEL
simim-0.3.10.dist-info/entry_points.txt
simim-0.3.10.dist-info/top_level.txt
simim-0.3.10.dist-info/RECORD
