Metadata-Version: 2.2
Name: simim
Version: 0.3.10
Summary: Code for simulating the radio, sub-mm and FIR sky
Author: R P Keenan
License: MIT License
Project-URL: Documentation, https://simim.readthedocs.io
Project-URL: Repository, https://github.com/rpkeenan/simim_public
Keywords: astronomy,line intensity mapping,LIM,extragalactic,galaxy evolution,light cone,radio astronomy,millimeter astronomy,submillimeter astronomy,FIR astronomy
Classifier: License :: OSI Approved :: MIT License
Classifier: Programming Language :: Python :: 3
Classifier: Topic :: Scientific/Engineering :: Astronomy
Requires-Python: >=3.6
License-File: LICENSE
Requires-Dist: astropy
Requires-Dist: h5py
Requires-Dist: importlib_resources
Requires-Dist: matplotlib
Requires-Dist: numpy
Requires-Dist: requests
Requires-Dist: scipy
